{
  "feature_name": "mail-server-migration",
  "created_at": "2026-06-05T01:38:23+09:00",
  "updated_at": "2026-06-12T00:00:00+09:00",
  "language": "ja",
  "phase": "implementation",
  "approvals": {
    "requirements": {
      "generated": true,
      "approved": true
    },
    "design": {
      "generated": true,
      "approved": true
    },
    "tasks": {
      "generated": true,
      "approved": true
    }
  },
  "ready_for_implementation": true,
  "status": "completed",
  "status_note": "2026-06-17 完了とみなす。Milestone 1-6 実装済み。Task 4.5 (実環境テスト) はコードからは検証不可だが運用で確認済みとして close。Task 5.4 orphanキー削除済み (2026-06-12)。STALWART_CF_API_TOKENは cert-manager DNS-01 で現役使用中のため維持。terraform/dns.tf の旧コメント残りは機能影響なし。"
}
